Orbeez/__init__.py
Orbeez/orbeez.py
Orbeez/orbitplot.py
Orbeez/planet.py
docs/conf.py
orbeez-1.1.3.dist-info/licenses/LICENSE
tests/__init__.py
tests/test_orbitplot.py
tests/test_planet.py
tests/end-to-end-tests/planet_end_to_end.py
tests/end-to-end-tests/trappist_end_to_end.py
orbeez-1.1.3.dist-info/METADATA
orbeez-1.1.3.dist-info/WHEEL
orbeez-1.1.3.dist-info/top_level.txt
orbeez-1.1.3.dist-info/RECORD
