Metadata-Version: 2.4
Name: Orbeez
Version: 1.1.3
License-File: LICENSE
Requires-Dist: numpy
Requires-Dist: matplotlib
Requires-Dist: scipy
Requires-Dist: pillow
Requires-Dist: astroquery
Requires-Dist: astropy
Requires-Dist: tqdm
Dynamic: license-file
